industrial_model/__init__.py
industrial_model/config.py
industrial_model/constants.py
industrial_model/py.typed
industrial_model/utils.py
industrial_model/cognite_adapters/__init__.py
industrial_model/cognite_adapters/aggregation_mapper.py
industrial_model/cognite_adapters/filter_mapper.py
industrial_model/cognite_adapters/models.py
industrial_model/cognite_adapters/optimizer.py
industrial_model/cognite_adapters/query_mapper.py
industrial_model/cognite_adapters/query_result_mapper.py
industrial_model/cognite_adapters/search_mapper.py
industrial_model/cognite_adapters/sort_mapper.py
industrial_model/cognite_adapters/upsert_mapper.py
industrial_model/cognite_adapters/utils.py
industrial_model/cognite_adapters/view_mapper.py
industrial_model/engines/__init__.py
industrial_model/engines/_internal.py
industrial_model/engines/async_engine.py
industrial_model/engines/engine.py
industrial_model/models/__init__.py
industrial_model/models/base.py
industrial_model/models/entities.py
industrial_model/models/schemas.py
industrial_model/models/utils.py
industrial_model/queries/__init__.py
industrial_model/queries/models.py
industrial_model/queries/params.py
industrial_model/queries/utils.py
industrial_model/statements/__init__.py
industrial_model/statements/expressions.py
industrial_model-1.2.2.dist-info/METADATA
industrial_model-1.2.2.dist-info/WHEEL
industrial_model-1.2.2.dist-info/licenses/LICENSE
industrial_model-1.2.2.dist-info/RECORD
