Metadata-Version: 2.4
Name: industrial-model
Version: 1.2.2
Summary: Industrial Model ORM
Project-URL: Homepage, https://github.com/lucasrosaalves/industrial-model
Project-URL: Source, https://github.com/lucasrosaalves/industrial-model
Author-email: Lucas Alves <lucasrosaalves@gmail.com>
License-File: LICENSE
Classifier: Programming Language :: Python
Classifier: Programming Language :: Python :: 3
Classifier: Programming Language :: Python :: 3 :: Only
Classifier: Programming Language :: Python :: 3.11
Classifier: Programming Language :: Python :: 3.12
Classifier: Programming Language :: Python :: 3.13
Classifier: Topic :: Database
Classifier: Topic :: Database :: Database Engines/Servers
Classifier: Typing :: Typed
Requires-Python: >=3.11
Requires-Dist: anyio>=4.9.0
Requires-Dist: cognite-sdk>=7.87.0
Requires-Dist: pydantic>=2.11.4
Requires-Dist: pyyaml>=6.0.2
